{
  "id": 16,
  "name": "Лебедева Наталья Игоревна",
  "dob": "1992-11-03",
  "sertifiedBarista": true,
  "skills": [
    "latte",
    "cappuccino",
    "flat white"
  ],
  "coffeeWithShugar": true,
  "lastCofee": "2025-09-29T21:30:52Z",
  "places": {
    "home": {
      "address": "Челябинск, пр. Ленина, д. 39, кв. 16",
      "coordinates": [
        55.1599,
        61.40255
      ]
    },
    "work": {
      "address": "Челябинск, ул. Кирова, д. 82",
      "coordinates": [
        55.16127,
        61.40038
      ]
    }
  },
  "experience": [
    {
      "id": 1,
      "name": "Уральская кофейня",
      "jobTitle": "Бариста",
      "start": "2014-07-10",
      "finish": "2018-04-15",
      "salary": 43000,
      "subordinates": 0,
      "isBoss": false,
      "awards": [],
      "responsibilities": [
        "Приготовление кофе",
        "Обслуживание клиентов"
      ]
    },
    {
      "id": 2,
      "name": "Coffee Style",
      "jobTitle": "Старший бариста",
      "start": "2018-05-01",
      "finish": null,
      "salary": 62000,
      "subordinates": 3,
      "isBoss": true,
      "awards": [],
      "responsibilities": [
        "Управление сменой",
        "Обучение персонала",
        "Контроль качества"
      ]
    }
  ],
  "referralIds": [
    9
  ]
}